{"description":"verify if we click on logo 404 page loads|protractor demo","passed":true,"pending":false,"os":"Windows","instanceId":6304,"browser":{"name":"chrome","version":"89.0.4389.82"},"message":"Passed.","trace":"","browserLogs":[{"level":"SEVERE","message":"https://sakshingp.github.io/assignment/index.html - Failed to load resource: the server responded with a status of 404 ()","timestamp":1615092684330,"type":""}],"screenShotFile":"004e00ee-0081-0053-00fa-009c00550043.png","timestamp":1615092684065,"duration":367}
